{
	"schemaVersion": 1,
	"id": "strong-leads",
	"version": "1.0.0",
	"name": "Strong Leads",
	"description": "Leads don't break.",
	"authors": [
		"Kim-Lan"
	],
	"contact": {
		"homepage": "https://github.com/Kim-Lan/",
		"sources": "https://github.com/Kim-Lan/strong-leads"
	},
	"license": "MIT",
	"icon": "assets/strongleads/icon.png",
	"environment": "*",
	"entrypoints": {
		"main": [
			"com.kimlan.strongleads.StrongLeads"
		]
	},
	"mixins": [
		"strongleads.mixins.json"
	],
	"depends": {
		"fabricloader": ">=0.16.9",
		"minecraft": "~1.21.4",
		"java": ">=21",
		"fabric-api": "*"
	},
	"suggests": {
		"another-mod": "*"
	}
}